javonet/__init__.py
javonet/core/__init__.py
javonet/core/callback/__init__.py
javonet/core/callback/callbackFunc.py
javonet/core/generator/__init__.py
javonet/core/generator/handler/AbstractGeneretatorHandler.py
javonet/core/generator/handler/CreateInstanceGeneratorHandler.py
javonet/core/generator/handler/GeneratorHandler.py
javonet/core/generator/handler/GetInstanceFieldGeneratorHandler.py
javonet/core/generator/handler/GetStaticFieldGeneratorHandler.py
javonet/core/generator/handler/GetTypeGeneratorHandler.py
javonet/core/generator/handler/Handlers.py
javonet/core/generator/handler/InvokeInstanceMethodGeneratorHandler.py
javonet/core/generator/handler/InvokeStaticMethodGeneratorHandler.py
javonet/core/generator/handler/__init__.py
javonet/core/generator/handler/shared/SharedArgumentNameHandler.py
javonet/core/generator/handler/shared/SharedClassInstanceHandler.py
javonet/core/generator/handler/shared/SharedClassNameHandler.py
javonet/core/generator/handler/shared/SharedMethodNameHandler.py
javonet/core/generator/handler/shared/SharedModifierHandler.py
javonet/core/generator/handler/shared/SharedReturnTypeHandler.py
javonet/core/generator/handler/shared/SharedTypeHandler.py
javonet/core/generator/handler/shared/__init__.py
javonet/core/generator/handler/shared/body/SharedBodyHandler.py
javonet/core/generator/handler/shared/body/SharedCreateInstanceBodyHandler.py
javonet/core/generator/handler/shared/body/SharedGetInstanceFieldBodyHandler.py
javonet/core/generator/handler/shared/body/SharedGetStaticFieldBodyHandler.py
javonet/core/generator/handler/shared/body/SharedGetTypeBodyHandler.py
javonet/core/generator/handler/shared/body/SharedInvokeInstanceMethodBodyHandler.py
javonet/core/generator/handler/shared/body/SharedInvokeStaticMethodBodyHandler.py
javonet/core/generator/handler/shared/body/__init__.py
javonet/core/generator/internal/CommonGenerator.py
javonet/core/generator/internal/PythonStringBuilder.py
javonet/core/generator/internal/SharedHandlerType.py
javonet_python_sdk-2.0.1.dist-info/METADATA
javonet_python_sdk-2.0.1.dist-info/WHEEL
javonet_python_sdk-2.0.1.dist-info/top_level.txt
javonet_python_sdk-2.0.1.dist-info/RECORD
