Metadata-Version: 2.1
Name: javonet-python-sdk
Version: 2.0.1
Summary: Javonet SDK for Python
Home-page: https://javonet.com
Author: SdNcenter Sp. z o.o.
Author-email: support@javonet.com
Classifier: Programming Language :: Python :: 3
Classifier: License :: OSI Approved :: MIT License
Classifier: Operating System :: OS Independent
Requires-Python: >=3.6
